{
  "slug": "geforce-rtx-5070",
  "name": "GeForce RTX 5070",
  "manufacturer": "nvidia",
  "architecture": "Blackwell",
  "release_date": "2025-03-05",
  "msrp_usd": 549,
  "cuda_cores": 6144,
  "stream_processors": null,
  "rt_cores": 48,
  "tensor_cores": 192,
  "memory_gb": 12,
  "memory_type": "GDDR7",
  "memory_bus_bit": 192,
  "memory_bandwidth_gbps": 672,
  "base_clock_mhz": 2164,
  "boost_clock_mhz": 2512,
  "tdp_w": 250,
  "pcie_version": "PCIe 5.0",
  "blender_score": null,
  "timespy_score": null,
  "verified": false,
  "source_urls": [
    "https://en.wikipedia.org/wiki/GeForce_RTX_50_series",
    "https://www.techpowerup.com/gpu-specs/geforce-rtx-5070.c4219"
  ]
}
