{
  "slug": "rtx-pro-5000-blackwell",
  "name": "RTX PRO 5000 Blackwell",
  "manufacturer": "nvidia",
  "architecture": "Blackwell",
  "release_date": "2025-12-09",
  "msrp_usd": 9999,
  "cuda_cores": 14080,
  "stream_processors": null,
  "rt_cores": 110,
  "tensor_cores": 440,
  "memory_gb": 72,
  "memory_type": "GDDR7",
  "memory_bus_bit": 384,
  "memory_bandwidth_gbps": 1344,
  "base_clock_mhz": 1485,
  "boost_clock_mhz": 2617,
  "tdp_w": 300,
  "pcie_version": "PCIe 5.0",
  "blender_score": null,
  "timespy_score": null,
  "verified": false,
  "source_urls": [
    "https://www.nvidia.com/en-us/products/workstations/professional-desktop-gpus/rtx-pro-6000-family/",
    "https://www.techpowerup.com/gpu-specs/rtx-pro-5000-blackwell.c4292"
  ]
}
