{
  "slug": "iphone-13-pro",
  "name": "iPhone 13 Pro",
  "brand": "apple",
  "soc": "apple-a15-bionic",
  "release_date": "2021-09-24",
  "msrp_usd": 999,
  "ram_gb": 6,
  "storage_options_gb": [128, 256, 512, 1024],
  "display": {
    "size_inch": 6.1,
    "resolution": "2532x1170",
    "refresh_hz": 120,
    "type": "Super Retina XDR OLED ProMotion",
    "brightness_nits": 1000,
    "ppi": 460
  },
  "cameras": [
    {"type": "main", "mp": 12, "aperture": 1.5, "ois": true},
    {"type": "ultrawide", "mp": 12, "aperture": 1.8, "ois": false},
    {"type": "telephoto", "mp": 12, "aperture": 2.8, "ois": true, "optical_zoom": 3},
    {"type": "selfie", "mp": 12, "aperture": 2.2}
  ],
  "battery_mah": 3095,
  "charging_wired_w": 20,
  "charging_wireless_w": 15,
  "weight_g": 203.0,
  "dimensions": {"height_mm": 146.7, "width_mm": 71.5, "depth_mm": 7.7},
  "ip_rating": "IP68",
  "os": "iOS",
  "os_version": "15",
  "connectivity": {"wifi": "Wi-Fi 6", "bluetooth": "5.0", "nfc": true, "usb": "Lightning"},
  "image_url": "https://cdn.jsdelivr.net/gh/GetTechAPI/images/smartphones/iphone-13-pro.webp",
  "verified": true,
  "source_urls": [
    "https://www.apple.com/iphone-13-pro/specs/",
    "https://en.wikipedia.org/wiki/IPhone_13_Pro"
  ]
}
