{
  "slug": "geforce-gtx-980",
  "name": "GeForce GTX 980",
  "manufacturer": "nvidia",
  "architecture": "Maxwell",
  "release_date": "2014-09-18",
  "msrp_usd": 549,
  "cuda_cores": 2048,
  "stream_processors": null,
  "rt_cores": null,
  "tensor_cores": null,
  "memory_gb": 4,
  "memory_type": "GDDR5",
  "memory_bus_bit": 256,
  "memory_bandwidth_gbps": 224,
  "base_clock_mhz": 1126,
  "boost_clock_mhz": 1216,
  "tdp_w": 165,
  "pcie_version": "PCIe 3.0",
  "blender_score": null,
  "timespy_score": null,
  "verified": false,
  "source_urls": [
    "https://en.wikipedia.org/wiki/GeForce_900_series",
    "https://www.techpowerup.com/gpu-specs/geforce-gtx-980.c2621"
  ]
}
